{"id":"ARTIemAZnY5u9Uc7k1rb5kBs241226","title":"中央气象台继续发布大风蓝色预警","content":"　　央视网消息：中央气象台12月26日06时继续发布大风蓝色预警。\n预计，12月26日08时至27日08时，西藏北部、青海南部和东北部、内蒙古中东部、河北北部、天津、辽宁西部、辽东半岛、山东半岛等地部分地区有5~6级风、阵风7~8级；渤海、渤海海峡、黄海北部和中部海域、东海南部海域、台湾海峡、台湾以东洋面、巴士海峡、南海北部海域将有7~8级、阵风9~10级的大风。\n12月27日08时至28日08时，西藏中北部、青海南部、内蒙古中东部、山西、河北北部、山东半岛等地部分地区有5~6级风、阵风7~8级；渤海南部、渤海海峡、黄海大部海域、东海东部和南部海域、台湾海峡、台湾以东洋面、巴士海峡、南海北部和中部海域、北部湾将有7~8级、阵风9~10级的大风。\n防御指南：\n1、中央气象台、中国海上搜救中心提醒受大风影响海域航行、作业的船舶，注意航行安全；\n2、森林、草场、城区防火部门做好防火准备，机场、铁路、公路等交通管理部门应采取措施保障交通安全；\n3、停止高空、水上户外作业和游乐活动，加固或妥善安置围板、棚架广告牌、简易设施等易被大风吹动的搭建物；\n4、行人与车辆不要在高大建筑物、广告牌等临时建筑物，或树的下方停留。","author":"央视网","cover":"ARTIemAZnY5u9Uc7k1rb5kBs241226","date":"2024/12/25","tags":["气象"],"zone":"气象"}