{"id":"ARTIamkxw4ECd49tJdcISB6w241208","title":"中央气象台继续发布大风蓝色预警","content":"央视网消息：据中央气象台网站消息，预计，12月8日20时至9日20时，西藏中西部、青海西南部、川西高原、新疆北部等地部分地区将有5~6级风，西藏中西部和青海西南部局地风力可达7~8级；东海南部、台湾海峡、台湾以东洋面、巴士海峡、南海大部海域将有7~8级、阵风9级的大风，其中台湾海峡部分海域的风力可达9级、阵风10级。 防御指南： 1、中央气象台、中国海上搜救中心提醒受大风影响海域航行、作业的船舶，注意航行安全； 2、森林、草场、城区防火部门做好防火准备，机场、铁路、公路等交通管理部门应采取措施保障交通安全； 3、停止高空、水上户外作业和游乐活动，加固或妥善安置围板、棚架广告牌、简易设施等易被大风吹动的搭建物； 4、行人与车辆不要在高大建筑物、广告牌等临时建筑物，或树的下方停留。","author":"央视网","cover":"ARTIamkxw4ECd49tJdcISB6w241208","date":"2024/12/07","tags":["气象"],"zone":"气象"}